{
  "errors": [],
  "warnings": [],
  "version": "4.41.5",
  "hash": "2ab5aad6739205f0338f",
  "publicPath": "/",
  "outputPath": "/var/www/site/v3/public",
  "assetsByChunkName": {
    "main": [
      "render-page.js",
      "render-page.js.map"
    ]
  },
  "assets": [
    {
      "name": "render-page.js",
      "size": 2293953,
      "chunks": [
        "main"
      ],
      "chunkNames": [
        "main"
      ],
      "info": {},
      "emitted": false
    },
    {
      "name": "render-page.js.map",
      "size": 2415106,
      "chunks": [
        "main"
      ],
      "chunkNames": [
        "main"
      ],
      "info": {
        "development": true
      },
      "emitted": false
    }
  ],
  "filteredAssets": 0,
  "entrypoints": {
    "main": {
      "chunks": [
        "main"
      ],
      "assets": [
        "render-page.js",
        "render-page.js.map"
      ],
      "children": {},
      "childAssets": {}
    }
  },
  "namedChunkGroups": {
    "main": {
      "chunks": [
        "main"
      ],
      "assets": [
        "render-page.js",
        "render-page.js.map"
      ],
      "children": {},
      "childAssets": {}
    }
  },
  "logging": {
    "webpack.buildChunkGraph.visitModules": {
      "entries": [],
      "filteredEntries": 2,
      "debug": false
    }
  },
  "children": []
}